odoo/addons/ssi_accountant_general_audit_ws_pe110/README.rst
odoo/addons/ssi_accountant_general_audit_ws_pe110/__init__.py
odoo/addons/ssi_accountant_general_audit_ws_pe110/__manifest__.py
odoo/addons/ssi_accountant_general_audit_ws_pe110/data/accountant_general_audit_worksheet_type_data.xml
odoo/addons/ssi_accountant_general_audit_ws_pe110/data/approval_template_data.xml
odoo/addons/ssi_accountant_general_audit_ws_pe110/data/ir_sequence_data.xml
odoo/addons/ssi_accountant_general_audit_ws_pe110/data/policy_template_data.xml
odoo/addons/ssi_accountant_general_audit_ws_pe110/data/sequence_template_data.xml
odoo/addons/ssi_accountant_general_audit_ws_pe110/models/__init__.py
odoo/addons/ssi_accountant_general_audit_ws_pe110/models/accountant_general_audit_ws_pe110.py
odoo/addons/ssi_accountant_general_audit_ws_pe110/models/accountant_general_audit_ws_pe1101.py
odoo/addons/ssi_accountant_general_audit_ws_pe110/models/accountant_general_audit_ws_pe1102.py
odoo/addons/ssi_accountant_general_audit_ws_pe110/models/accountant_general_audit_ws_pe11021.py
odoo/addons/ssi_accountant_general_audit_ws_pe110/models/accountant_general_audit_ws_pe11022.py
odoo/addons/ssi_accountant_general_audit_ws_pe110/models/accountant_general_audit_ws_pe1103.py
odoo/addons/ssi_accountant_general_audit_ws_pe110/models/accountant_general_audit_ws_pe1104.py
odoo/addons/ssi_accountant_general_audit_ws_pe110/security/ir.model.access.csv
odoo/addons/ssi_accountant_general_audit_ws_pe110/security/ir_module_category_data.xml
odoo/addons/ssi_accountant_general_audit_ws_pe110/security/ir_rule_data.xml
odoo/addons/ssi_accountant_general_audit_ws_pe110/security/res_group_data.xml
odoo/addons/ssi_accountant_general_audit_ws_pe110/static/description/icon.png
odoo/addons/ssi_accountant_general_audit_ws_pe110/views/accountant_general_audit_ws_pe1101_views.xml
odoo/addons/ssi_accountant_general_audit_ws_pe110/views/accountant_general_audit_ws_pe11021_views.xml
odoo14_addon_ssi_accountant_general_audit_ws_pe110-14.0.1.0.2.dev1.dist-info/METADATA
odoo14_addon_ssi_accountant_general_audit_ws_pe110-14.0.1.0.2.dev1.dist-info/WHEEL
odoo14_addon_ssi_accountant_general_audit_ws_pe110-14.0.1.0.2.dev1.dist-info/top_level.txt
odoo14_addon_ssi_accountant_general_audit_ws_pe110-14.0.1.0.2.dev1.dist-info/RECORD
